{
    "id": 122919,
    "title": "Pre-Season Video: HRC",
    "slug": "pre-season-video-hrc-122919",
    "excerpt": "Honda HRC prepare for Anaheim 1.",
    "created": "2019-12-30 18:11:52",
    "modified": "2019-12-30 21:03:05",
    "url": "\/122919\/pre-season-video-hrc",
    "categories": [
        645496159,
        645496800
    ],
    "category": {
        "id": 645496159,
        "active": true,
        "slug": "supercross",
        "source": "https:\/\/mxvice-en.com\/wp-json\/wp\/v2\/posts?categories=645496159",
        "name": {
            "short": "Supercross",
            "long": "Monster Energy Supercross",
            "nav": "Monster Energy Supercross"
        },
        "components": null,
        "title": "Monster Energy Supercross",
        "description": "",
        "parent": false,
        "url": "channel\/supercross",
        "wp_count": 960,
        "count": 12
    },
    "domain": "all",
    "video": true,
    "author": "Lewis Phillips",
    "content": "<table>\n<tbody>\n<tr>\n<td>\n<p dir=\"ltr\" style=\"text-align: center;\"><a href=\"https:\/\/www.youtube.com\/channel\/UCxeEsENwOA2ni3hPqJBhYKg\"><strong>Subscribe to MX Vice on YouTube.<\/strong><\/a><\/p>\n<\/td>\n<\/tr>\n<\/tbody>\n<\/table>\n<div dir=\"ltr\">\n<table>\n<tbody>\n<tr>\n<td>\n<p dir=\"ltr\" style=\"text-align: center;\"><a href=\"https:\/\/instagram.com\/mxvice\/\"><strong>Follow @MXVice on Instagram.<\/strong><\/a><\/p>\n<\/td>\n<\/tr>\n<\/tbody>\n<\/table>\n<\/div>\n<p>The opening round of AMA Supercross is like the first day of school, and Team Honda HRC has done the off-season homework. Heading into Anaheim 1, riders Ken Roczen and Justin Brayton are armed with speed, health and experience, all of which they are ready to put to good use to finish top-of-class.\u00a0<i>\u2013\u00a0Honda Racing Corporation<\/i><\/p>\n<figure class=\"video-container\"><iframe width=\"640\" height=\"360\" src=\"https:\/\/www.youtube.com\/embed\/dhjn7C-fCtM?rel=0&amp;wmode=transparent\" frameborder=\"0\"><\/iframe><\/figure>\n<p><strong>Video: Honda Motorcycles & ATVs | Lead Image: Honda Racing Corporation<\/strong><\/p>",
    "date": "Monday 30, December 2019",
    "updated": true,
    "preamble": "Subscribe to MX Vice on YouTube. Follow @MXVice on Instagram. The opening round of AMA Supercross is like the first day of sc...",
    "index": false,
    "tags": [],
    "featured_media_caption": ""
}